django_batch_uploader
