Metadata-Version: 1.1
Name: django-batch-uploader
Version: 0.12.1
Summary: Batch Uploading Mechanism for Django Admin
Home-page: https://github.com/ninapavlich/django-batch-uploader
Author: Nina Pavlich
Author-email: nina@ninalp.com
License: MIT
Keywords: libraries,web development
Platform: UNKNOWN
Classifier: Development Status :: 4 - Beta
Classifier: Environment :: Web Environment
Classifier: Framework :: Django
Classifier: Intended Audience :: Developers
Classifier: License :: OSI Approved :: MIT License
Classifier: Natural Language :: English
Classifier: Operating System :: OS Independent
Classifier: Programming Language :: Python
